{"cameraMode":{"drawMode":0,"name":"Shaded","section":"Shading Mode"},"sceneLighting":true,"audioPlay":false,"sceneViewState":{"m_AlwaysRefresh":false,"showFog":true,"showSkybox":true,"showFlares":true,"showImageEffects":true,"showParticleSystems":true,"showVisualEffectGraphs":true,"m_FxEnabled":true},"in2DMode":false,"pivot":{"x":8.34635066986084,"y":29.113300323486329,"z":-47.877254486083987},"rotation":{"x":0.297807514667511,"y":-0.0729408711194992,"z":0.022827796638011934,"w":0.9515635371208191},"size":7.971590518951416,"orthographic":false}